MANIFEST.in
README.rst
setup.py
docs/HISTORY.txt
docs/INSTALL.txt
docs/LICENSE.GPL
docs/LICENSE.txt
rt/__init__.py
rt.zps.egg-info/PKG-INFO
rt.zps.egg-info/SOURCES.txt
rt.zps.egg-info/dependency_links.txt
rt.zps.egg-info/entry_points.txt
rt.zps.egg-info/not-zip-safe
rt.zps.egg-info/requires.txt
rt.zps.egg-info/top_level.txt
rt/zps/__init__.py
rt/zps/streams.py
rt/zps/zps
rt/zps/app/__init__.py
rt/zps/app/finder.py
rt/zps/app/report.py
rt/zps/templates/__init__.py
rt/zps/templates/errors.py
rt/zps/templates/report.py
rt/zps/templates/usage.py
rt/zps/tests/0zope.conf
rt/zps/tests/1zope.conf
rt/zps/tests/__init__.py
rt/zps/tests/mocks.py
rt/zps/tests/test_zps.py