Metadata-Version: 1.1
Name: rt.zps
Version: 0.9.6
Summary: A zope processes inspector
Home-page: http://github.com/RedTurtle/rt.zps
Author: alert
Author-email: alessandro.pisa@redturtle.it
License: GPL
Platform: UNKNOWN
Classifier: Programming Language :: Python
Classifier: Programming Language :: Python :: 2
Classifier: Programming Language :: Python :: 3
